{
  "path": "ocr-needed/43_Modern.pdf",
  "name": "43_Modern",
  "readableName": "43 Modern",
  "category": "Modern",
  "totalPosters": 349,
  "numLandscapePosters": 349,
  "numPortraitPosters": 0,
  "usedLandscapeForSample": true,
  "posters": [
    {
      "pdfName": "43_Modern",
      "pageNo": 1,
      "index": 1,
      "code": "25725",
      "id": "43_Modern--i1--25725",
      "imageFile": "43_Modern--i1--25725--1703f.jpg",
      "imageSize": [
        500,
        353
      ]
    },
    {
      "pdfName": "43_Modern",
      "pageNo": 2,
      "index": 2,
      "code": "25726",
      "id": "43_Modern--i2--25726",
      "imageFile": "43_Modern--i2--25726--444ad.jpg",
      "imageSize": [
        500,
        353
      ]
    },
    {
      "pdfName": "43_Modern",
      "pageNo": 3,
      "index": 3,
      "code": "25727",
      "id": "43_Modern--i3--25727",
      "imageFile": "43_Modern--i3--25727--bfd9c.jpg",
      "imageSize": [
        500,
        353
      ]
    },
    {
      "pdfName": "43_Modern",
      "pageNo": 4,
      "index": 4,
      "code": "25728",
      "id": "43_Modern--i4--25728",
      "imageFile": "43_Modern--i4--25728--be825.jpg",
      "imageSize": [
        500,
        353
      ]
    },
    {
      "pdfName": "43_Modern",
      "pageNo": 5,
      "index": 5,
      "code": "25729",
      "id": "43_Modern--i5--25729",
      "imageFile": "43_Modern--i5--25729--07fcd.jpg",
      "imageSize": [
        500,
        353
      ]
    },
    {
      "pdfName": "43_Modern",
      "pageNo": 6,
      "index": 6,
      "code": "25730",
      "id": "43_Modern--i6--25730",
      "imageFile": "43_Modern--i6--25730--38dc9.jpg",
      "imageSize": [
        500,
        353
      ]
    },
    {
      "pdfName": "43_Modern",
      "pageNo": 7,
      "index": 7,
      "code": "25731",
      "id": "43_Modern--i7--25731",
      "imageFile": "43_Modern--i7--25731--68332.jpg",
      "imageSize": [
        500,
        353
      ]
    },
    {
      "pdfName": "43_Modern",
      "pageNo": 8,
      "index": 8,
      "code": "25732",
      "id": "43_Modern--i8--25732",
      "imageFile": "43_Modern--i8--25732--0125c.jpg",
      "imageSize": [
        500,
        353
      ]
    },
    {
      "pdfName": "43_Modern",
      "pageNo": 9,
      "index": 9,
      "code": "25733",
      "id": "43_Modern--i9--25733",
      "imageFile": "43_Modern--i9--25733--9c4b2.jpg",
      "imageSize": [
        500,
        353
      ]
    },
    {
      "pdfName": "43_Modern",
      "pageNo": 10,
      "index": 10,
      "code": "25734",
      "id": "43_Modern--i10--25734",
      "imageFile": "43_Modern--i10--25734--cc998.jpg",
      "imageSize": [
        500,
        353
      ]
    },
    {
      "pdfName": "43_Modern",
      "pageNo": 11,
      "index": 11,
      "code": "25735",
      "id": "43_Modern--i11--25735",
      "imageFile": "43_Modern--i11--25735--1f13f.jpg",
      "imageSize": [
        500,
        353
      ]
    },
    {
      "pdfName": "43_Modern",
      "pageNo": 12,
      "index": 12,
      "code": "25736",
      "id": "43_Modern--i12--25736",
      "imageFile": "43_Modern--i12--25736--dd6f4.jpg",
      "imageSize": [
        500,
        353
      ]
    },
    {
      "pdfName": "43_Modern",
      "pageNo": 13,
      "index": 13,
      "code": "25737",
      "id": "43_Modern--i13--25737",
      "imageFile": "43_Modern--i13--25737--34c2c.jpg",
      "imageSize": [
        500,
        353
      ]
    },
    {
      "pdfName": "43_Modern",
      "pageNo": 14,
      "index": 14,
      "code": "25738",
      "id": "43_Modern--i14--25738",
      "imageFile": "43_Modern--i14--25738--fb094.jpg",
      "imageSize": [
        500,
        353
      ]
    },
    {
      "pdfName": "43_Modern",
      "pageNo": 15,
      "index": 15,
      "code": "25739",
      "id": "43_Modern--i15--25739",
      "imageFile": "43_Modern--i15--25739--204da.jpg",
      "imageSize": [
        500,
        353
      ]
    },
    {
      "pdfName": "43_Modern",
      "pageNo": 16,
      "index": 16,
      "code": "25740",
      "id": "43_Modern--i16--25740",
      "imageFile": "43_Modern--i16--25740--71955.jpg",
      "imageSize": [
        500,
        353
      ]
    },
    {
      "pdfName": "43_Modern",
      "pageNo": 17,
      "index": 17,
      "code": "25741",
      "id": "43_Modern--i17--25741",
      "imageFile": "43_Modern--i17--25741--24acc.jpg",
      "imageSize": [
        500,
        353
      ]
    },
    {
      "pdfName": "43_Modern",
      "pageNo": 18,
      "index": 18,
      "code": "25742",
      "id": "43_Modern--i18--25742",
      "imageFile": "43_Modern--i18--25742--e017c.jpg",
      "imageSize": [
        500,
        353
      ]
    },
    {
      "pdfName": "43_Modern",
      "pageNo": 19,
      "index": 19,
      "code": "25743",
      "id": "43_Modern--i19--25743",
      "imageFile": "43_Modern--i19--25743--39489.jpg",
      "imageSize": [
        500,
        353
      ]
    },
    {
      "pdfName": "43_Modern",
      "pageNo": 20,
      "index": 20,
      "code": "25744",
      "id": "43_Modern--i20--25744",
      "imageFile": "43_Modern--i20--25744--ac781.jpg",
      "imageSize": [
        500,
        353
      ]
    },
    {
      "pdfName": "43_Modern",
      "pageNo": 21,
      "index": 21,
      "code": "25745",
      "id": "43_Modern--i21--25745",
      "imageFile": "43_Modern--i21--25745--2dec4.jpg",
      "imageSize": [
        500,
        353
      ]
    },
    {
      "pdfName": "43_Modern",
      "pageNo": 22,
      "index": 22,
      "code": "25746",
      "id": "43_Modern--i22--25746",
      "imageFile": "43_Modern--i22--25746--dfc7c.jpg",
      "imageSize": [
        500,
        353
      ]
    },
    {
      "pdfName": "43_Modern",
      "pageNo": 23,
      "index": 23,
      "code": "25747",
      "id": "43_Modern--i23--25747",
      "imageFile": "43_Modern--i23--25747--c9b32.jpg",
      "imageSize": [
        500,
        353
      ]
    },
    {
      "pdfName": "43_Modern",
      "pageNo": 24,
      "index": 24,
      "code": "25748",
      "id": "43_Modern--i24--25748",
      "imageFile": "43_Modern--i24--25748--cd717.jpg",
      "imageSize": [
        500,
        353
      ]
    },
    {
      "pdfName": "43_Modern",
      "pageNo": 25,
      "index": 25,
      "code": "25749",
      "id": "43_Modern--i25--25749",
      "imageFile": "43_Modern--i25--25749--980bf.jpg",
      "imageSize": [
        500,
        353
      ]
    },
    {
      "pdfName": "43_Modern",
      "pageNo": 26,
      "index": 26,
      "code": "25750",
      "id": "43_Modern--i26--25750",
      "imageFile": "43_Modern--i26--25750--aaf8f.jpg",
      "imageSize": [
        500,
        353
      ]
    },
    {
      "pdfName": "43_Modern",
      "pageNo": 27,
      "index": 27,
      "code": "25751",
      "id": "43_Modern--i27--25751",
      "imageFile": "43_Modern--i27--25751--4cd9a.jpg",
      "imageSize": [
        500,
        353
      ]
    },
    {
      "pdfName": "43_Modern",
      "pageNo": 28,
      "index": 28,
      "code": "25752",
      "id": "43_Modern--i28--25752",
      "imageFile": "43_Modern--i28--25752--196cb.jpg",
      "imageSize": [
        500,
        353
      ]
    },
    {
      "pdfName": "43_Modern",
      "pageNo": 29,
      "index": 29,
      "code": "25753",
      "id": "43_Modern--i29--25753",
      "imageFile": "43_Modern--i29--25753--1f16f.jpg",
      "imageSize": [
        500,
        353
      ]
    },
    {
      "pdfName": "43_Modern",
      "pageNo": 30,
      "index": 30,
      "code": "25754",
      "id": "43_Modern--i30--25754",
      "imageFile": "43_Modern--i30--25754--abb11.jpg",
      "imageSize": [
        500,
        353
      ]
    },
    {
      "pdfName": "43_Modern",
      "pageNo": 31,
      "index": 31,
      "code": "25755",
      "id": "43_Modern--i31--25755",
      "imageFile": "43_Modern--i31--25755--2b422.jpg",
      "imageSize": [
        500,
        353
      ]
    },
    {
      "pdfName": "43_Modern",
      "pageNo": 32,
      "index": 32,
      "code": "25756",
      "id": "43_Modern--i32--25756",
      "imageFile": "43_Modern--i32--25756--d1044.jpg",
      "imageSize": [
        500,
        353
      ]
    },
    {
      "pdfName": "43_Modern",
      "pageNo": 33,
      "index": 33,
      "code": "25757",
      "id": "43_Modern--i33--25757",
      "imageFile": "43_Modern--i33--25757--38d48.jpg",
      "imageSize": [
        500,
        353
      ]
    },
    {
      "pdfName": "43_Modern",
      "pageNo": 34,
      "index": 34,
      "code": "25758",
      "id": "43_Modern--i34--25758",
      "imageFile": "43_Modern--i34--25758--53945.jpg",
      "imageSize": [
        500,
        353
      ]
    },
    {
      "pdfName": "43_Modern",
      "pageNo": 35,
      "index": 35,
      "code": "25759",
      "id": "43_Modern--i35--25759",
      "imageFile": "43_Modern--i35--25759--f6717.jpg",
      "imageSize": [
        500,
        353
      ]
    },
    {
      "pdfName": "43_Modern",
      "pageNo": 36,
      "index": 36,
      "code": "25760",
      "id": "43_Modern--i36--25760",
      "imageFile": "43_Modern--i36--25760--c3ece.jpg",
      "imageSize": [
        500,
        353
      ]
    },
    {
      "pdfName": "43_Modern",
      "pageNo": 37,
      "index": 37,
      "code": "25761",
      "id": "43_Modern--i37--25761",
      "imageFile": "43_Modern--i37--25761--badbd.jpg",
      "imageSize": [
        500,
        353
      ]
    },
    {
      "pdfName": "43_Modern",
      "pageNo": 38,
      "index": 38,
      "code": "25762",
      "id": "43_Modern--i38--25762",
      "imageFile": "43_Modern--i38--25762--8e12d.jpg",
      "imageSize": [
        500,
        353
      ]
    },
    {
      "pdfName": "43_Modern",
      "pageNo": 39,
      "index": 39,
      "code": "25763",
      "id": "43_Modern--i39--25763",
      "imageFile": "43_Modern--i39--25763--7132e.jpg",
      "imageSize": [
        500,
        353
      ]
    },
    {
      "pdfName": "43_Modern",
      "pageNo": 40,
      "index": 40,
      "code": "25764",
      "id": "43_Modern--i40--25764",
      "imageFile": "43_Modern--i40--25764--279ed.jpg",
      "imageSize": [
        500,
        353
      ]
    },
    {
      "pdfName": "43_Modern",
      "pageNo": 41,
      "index": 41,
      "code": "25765",
      "id": "43_Modern--i41--25765",
      "imageFile": "43_Modern--i41--25765--22d5e.jpg",
      "imageSize": [
        500,
        353
      ]
    },
    {
      "pdfName": "43_Modern",
      "pageNo": 42,
      "index": 42,
      "code": "25766",
      "id": "43_Modern--i42--25766",
      "imageFile": "43_Modern--i42--25766--2a1b7.jpg",
      "imageSize": [
        500,
        353
      ]
    },
    {
      "pdfName": "43_Modern",
      "pageNo": 43,
      "index": 43,
      "code": "25767",
      "id": "43_Modern--i43--25767",
      "imageFile": "43_Modern--i43--25767--9d942.jpg",
      "imageSize": [
        500,
        353
      ]
    },
    {
      "pdfName": "43_Modern",
      "pageNo": 44,
      "index": 44,
      "code": "25768",
      "id": "43_Modern--i44--25768",
      "imageFile": "43_Modern--i44--25768--8cd52.jpg",
      "imageSize": [
        500,
        353
      ]
    },
    {
      "pdfName": "43_Modern",
      "pageNo": 45,
      "index": 45,
      "code": "25769",
      "id": "43_Modern--i45--25769",
      "imageFile": "43_Modern--i45--25769--ce47a.jpg",
      "imageSize": [
        500,
        353
      ]
    },
    {
      "pdfName": "43_Modern",
      "pageNo": 46,
      "index": 46,
      "code": "25770",
      "id": "43_Modern--i46--25770",
      "imageFile": "43_Modern--i46--25770--f77d0.jpg",
      "imageSize": [
        500,
        353
      ]
    },
    {
      "pdfName": "43_Modern",
      "pageNo": 47,
      "index": 47,
      "code": "25771",
      "id": "43_Modern--i47--25771",
      "imageFile": "43_Modern--i47--25771--cc9d4.jpg",
      "imageSize": [
        500,
        353
      ]
    },
    {
      "pdfName": "43_Modern",
      "pageNo": 48,
      "index": 48,
      "code": "25772",
      "id": "43_Modern--i48--25772",
      "imageFile": "43_Modern--i48--25772--eb818.jpg",
      "imageSize": [
        500,
        353
      ]
    },
    {
      "pdfName": "43_Modern",
      "pageNo": 49,
      "index": 49,
      "code": "25773",
      "id": "43_Modern--i49--25773",
      "imageFile": "43_Modern--i49--25773--6b554.jpg",
      "imageSize": [
        500,
        353
      ]
    },
    {
      "pdfName": "43_Modern",
      "pageNo": 50,
      "index": 50,
      "code": "25774",
      "id": "43_Modern--i50--25774",
      "imageFile": "43_Modern--i50--25774--1313f.jpg",
      "imageSize": [
        500,
        353
      ]
    },
    {
      "pdfName": "43_Modern",
      "pageNo": 51,
      "index": 51,
      "code": "25775",
      "id": "43_Modern--i51--25775",
      "imageFile": "43_Modern--i51--25775--d1d22.jpg",
      "imageSize": [
        500,
        353
      ]
    },
    {
      "pdfName": "43_Modern",
      "pageNo": 52,
      "index": 52,
      "code": "25776",
      "id": "43_Modern--i52--25776",
      "imageFile": "43_Modern--i52--25776--f0b2c.jpg",
      "imageSize": [
        500,
        353
      ]
    },
    {
      "pdfName": "43_Modern",
      "pageNo": 53,
      "index": 53,
      "code": "25777",
      "id": "43_Modern--i53--25777",
      "imageFile": "43_Modern--i53--25777--765dd.jpg",
      "imageSize": [
        500,
        353
      ]
    },
    {
      "pdfName": "43_Modern",
      "pageNo": 54,
      "index": 54,
      "code": "25778",
      "id": "43_Modern--i54--25778",
      "imageFile": "43_Modern--i54--25778--e06a2.jpg",
      "imageSize": [
        500,
        353
      ]
    },
    {
      "pdfName": "43_Modern",
      "pageNo": 55,
      "index": 55,
      "code": "25779",
      "id": "43_Modern--i55--25779",
      "imageFile": "43_Modern--i55--25779--676f1.jpg",
      "imageSize": [
        500,
        353
      ]
    },
    {
      "pdfName": "43_Modern",
      "pageNo": 56,
      "index": 56,
      "code": "25780",
      "id": "43_Modern--i56--25780",
      "imageFile": "43_Modern--i56--25780--1b8d8.jpg",
      "imageSize": [
        500,
        353
      ]
    },
    {
      "pdfName": "43_Modern",
      "pageNo": 57,
      "index": 57,
      "code": "25781",
      "id": "43_Modern--i57--25781",
      "imageFile": "43_Modern--i57--25781--93b04.jpg",
      "imageSize": [
        500,
        353
      ]
    },
    {
      "pdfName": "43_Modern",
      "pageNo": 58,
      "index": 58,
      "code": "25782",
      "id": "43_Modern--i58--25782",
      "imageFile": "43_Modern--i58--25782--b8cfd.jpg",
      "imageSize": [
        500,
        353
      ]
    },
    {
      "pdfName": "43_Modern",
      "pageNo": 59,
      "index": 59,
      "code": "25783",
      "id": "43_Modern--i59--25783",
      "imageFile": "43_Modern--i59--25783--8510b.jpg",
      "imageSize": [
        500,
        353
      ]
    },
    {
      "pdfName": "43_Modern",
      "pageNo": 60,
      "index": 60,
      "code": "25784",
      "id": "43_Modern--i60--25784",
      "imageFile": "43_Modern--i60--25784--cba2a.jpg",
      "imageSize": [
        500,
        353
      ]
    },
    {
      "pdfName": "43_Modern",
      "pageNo": 61,
      "index": 61,
      "code": "25785",
      "id": "43_Modern--i61--25785",
      "imageFile": "43_Modern--i61--25785--9a6b5.jpg",
      "imageSize": [
        500,
        353
      ]
    },
    {
      "pdfName": "43_Modern",
      "pageNo": 62,
      "index": 62,
      "code": "25786",
      "id": "43_Modern--i62--25786",
      "imageFile": "43_Modern--i62--25786--58ed3.jpg",
      "imageSize": [
        500,
        353
      ]
    },
    {
      "pdfName": "43_Modern",
      "pageNo": 63,
      "index": 63,
      "code": "25787",
      "id": "43_Modern--i63--25787",
      "imageFile": "43_Modern--i63--25787--65538.jpg",
      "imageSize": [
        500,
        353
      ]
    },
    {
      "pdfName": "43_Modern",
      "pageNo": 64,
      "index": 64,
      "code": "25788",
      "id": "43_Modern--i64--25788",
      "imageFile": "43_Modern--i64--25788--f3f75.jpg",
      "imageSize": [
        500,
        353
      ]
    },
    {
      "pdfName": "43_Modern",
      "pageNo": 65,
      "index": 65,
      "code": "25789",
      "id": "43_Modern--i65--25789",
      "imageFile": "43_Modern--i65--25789--4b7bf.jpg",
      "imageSize": [
        500,
        353
      ]
    },
    {
      "pdfName": "43_Modern",
      "pageNo": 66,
      "index": 66,
      "code": "25790",
      "id": "43_Modern--i66--25790",
      "imageFile": "43_Modern--i66--25790--e8283.jpg",
      "imageSize": [
        500,
        353
      ]
    },
    {
      "pdfName": "43_Modern",
      "pageNo": 67,
      "index": 67,
      "code": "25791",
      "id": "43_Modern--i67--25791",
      "imageFile": "43_Modern--i67--25791--6ef3a.jpg",
      "imageSize": [
        500,
        353
      ]
    },
    {
      "pdfName": "43_Modern",
      "pageNo": 68,
      "index": 68,
      "code": "25792",
      "id": "43_Modern--i68--25792",
      "imageFile": "43_Modern--i68--25792--011d7.jpg",
      "imageSize": [
        500,
        353
      ]
    },
    {
      "pdfName": "43_Modern",
      "pageNo": 69,
      "index": 69,
      "code": "25793",
      "id": "43_Modern--i69--25793",
      "imageFile": "43_Modern--i69--25793--819bd.jpg",
      "imageSize": [
        500,
        353
      ]
    },
    {
      "pdfName": "43_Modern",
      "pageNo": 70,
      "index": 70,
      "code": "25794",
      "id": "43_Modern--i70--25794",
      "imageFile": "43_Modern--i70--25794--694ab.jpg",
      "imageSize": [
        500,
        353
      ]
    },
    {
      "pdfName": "43_Modern",
      "pageNo": 71,
      "index": 71,
      "code": "25795",
      "id": "43_Modern--i71--25795",
      "imageFile": "43_Modern--i71--25795--ff628.jpg",
      "imageSize": [
        500,
        353
      ]
    },
    {
      "pdfName": "43_Modern",
      "pageNo": 72,
      "index": 72,
      "code": "25796",
      "id": "43_Modern--i72--25796",
      "imageFile": "43_Modern--i72--25796--43c3d.jpg",
      "imageSize": [
        500,
        353
      ]
    },
    {
      "pdfName": "43_Modern",
      "pageNo": 73,
      "index": 73,
      "code": "25797",
      "id": "43_Modern--i73--25797",
      "imageFile": "43_Modern--i73--25797--3350f.jpg",
      "imageSize": [
        500,
        353
      ]
    },
    {
      "pdfName": "43_Modern",
      "pageNo": 74,
      "index": 74,
      "code": "25798",
      "id": "43_Modern--i74--25798",
      "imageFile": "43_Modern--i74--25798--cba64.jpg",
      "imageSize": [
        500,
        353
      ]
    },
    {
      "pdfName": "43_Modern",
      "pageNo": 75,
      "index": 75,
      "code": "25799",
      "id": "43_Modern--i75--25799",
      "imageFile": "43_Modern--i75--25799--91662.jpg",
      "imageSize": [
        500,
        353
      ]
    },
    {
      "pdfName": "43_Modern",
      "pageNo": 76,
      "index": 76,
      "code": "25800",
      "id": "43_Modern--i76--25800",
      "imageFile": "43_Modern--i76--25800--b10db.jpg",
      "imageSize": [
        500,
        353
      ]
    },
    {
      "pdfName": "43_Modern",
      "pageNo": 77,
      "index": 77,
      "code": "25801",
      "id": "43_Modern--i77--25801",
      "imageFile": "43_Modern--i77--25801--adca7.jpg",
      "imageSize": [
        500,
        353
      ]
    },
    {
      "pdfName": "43_Modern",
      "pageNo": 78,
      "index": 78,
      "code": "25802",
      "id": "43_Modern--i78--25802",
      "imageFile": "43_Modern--i78--25802--05f6a.jpg",
      "imageSize": [
        500,
        353
      ]
    },
    {
      "pdfName": "43_Modern",
      "pageNo": 79,
      "index": 79,
      "code": "25803",
      "id": "43_Modern--i79--25803",
      "imageFile": "43_Modern--i79--25803--a5d62.jpg",
      "imageSize": [
        500,
        353
      ]
    },
    {
      "pdfName": "43_Modern",
      "pageNo": 80,
      "index": 80,
      "code": "25804",
      "id": "43_Modern--i80--25804",
      "imageFile": "43_Modern--i80--25804--51dd5.jpg",
      "imageSize": [
        500,
        353
      ]
    },
    {
      "pdfName": "43_Modern",
      "pageNo": 81,
      "index": 81,
      "code": "25805",
      "id": "43_Modern--i81--25805",
      "imageFile": "43_Modern--i81--25805--f3d00.jpg",
      "imageSize": [
        500,
        353
      ]
    },
    {
      "pdfName": "43_Modern",
      "pageNo": 82,
      "index": 82,
      "code": "25806",
      "id": "43_Modern--i82--25806",
      "imageFile": "43_Modern--i82--25806--ad84d.jpg",
      "imageSize": [
        500,
        353
      ]
    },
    {
      "pdfName": "43_Modern",
      "pageNo": 83,
      "index": 83,
      "code": "25807",
      "id": "43_Modern--i83--25807",
      "imageFile": "43_Modern--i83--25807--285f2.jpg",
      "imageSize": [
        500,
        353
      ]
    },
    {
      "pdfName": "43_Modern",
      "pageNo": 84,
      "index": 84,
      "code": "25808",
      "id": "43_Modern--i84--25808",
      "imageFile": "43_Modern--i84--25808--65249.jpg",
      "imageSize": [
        500,
        353
      ]
    },
    {
      "pdfName": "43_Modern",
      "pageNo": 85,
      "index": 85,
      "code": "25809",
      "id": "43_Modern--i85--25809",
      "imageFile": "43_Modern--i85--25809--7d500.jpg",
      "imageSize": [
        500,
        353
      ]
    },
    {
      "pdfName": "43_Modern",
      "pageNo": 86,
      "index": 86,
      "code": "25810",
      "id": "43_Modern--i86--25810",
      "imageFile": "43_Modern--i86--25810--3aeb9.jpg",
      "imageSize": [
        500,
        353
      ]
    },
    {
      "pdfName": "43_Modern",
      "pageNo": 87,
      "index": 87,
      "code": "25811",
      "id": "43_Modern--i87--25811",
      "imageFile": "43_Modern--i87--25811--fcc35.jpg",
      "imageSize": [
        500,
        353
      ]
    },
    {
      "pdfName": "43_Modern",
      "pageNo": 88,
      "index": 88,
      "code": "25812",
      "id": "43_Modern--i88--25812",
      "imageFile": "43_Modern--i88--25812--a9898.jpg",
      "imageSize": [
        500,
        353
      ]
    },
    {
      "pdfName": "43_Modern",
      "pageNo": 89,
      "index": 89,
      "code": "25813",
      "id": "43_Modern--i89--25813",
      "imageFile": "43_Modern--i89--25813--1fc9f.jpg",
      "imageSize": [
        500,
        353
      ]
    },
    {
      "pdfName": "43_Modern",
      "pageNo": 90,
      "index": 90,
      "code": "25814",
      "id": "43_Modern--i90--25814",
      "imageFile": "43_Modern--i90--25814--7d974.jpg",
      "imageSize": [
        500,
        353
      ]
    },
    {
      "pdfName": "43_Modern",
      "pageNo": 91,
      "index": 91,
      "code": "25815",
      "id": "43_Modern--i91--25815",
      "imageFile": "43_Modern--i91--25815--706b4.jpg",
      "imageSize": [
        500,
        353
      ]
    },
    {
      "pdfName": "43_Modern",
      "pageNo": 92,
      "index": 92,
      "code": "25816",
      "id": "43_Modern--i92--25816",
      "imageFile": "43_Modern--i92--25816--3e77f.jpg",
      "imageSize": [
        500,
        353
      ]
    },
    {
      "pdfName": "43_Modern",
      "pageNo": 93,
      "index": 93,
      "code": "25817",
      "id": "43_Modern--i93--25817",
      "imageFile": "43_Modern--i93--25817--2b4c7.jpg",
      "imageSize": [
        500,
        353
      ]
    },
    {
      "pdfName": "43_Modern",
      "pageNo": 94,
      "index": 94,
      "code": "25818",
      "id": "43_Modern--i94--25818",
      "imageFile": "43_Modern--i94--25818--99be6.jpg",
      "imageSize": [
        500,
        353
      ]
    },
    {
      "pdfName": "43_Modern",
      "pageNo": 95,
      "index": 95,
      "code": "25819",
      "id": "43_Modern--i95--25819",
      "imageFile": "43_Modern--i95--25819--196c7.jpg",
      "imageSize": [
        500,
        353
      ]
    },
    {
      "pdfName": "43_Modern",
      "pageNo": 96,
      "index": 96,
      "code": "25820",
      "id": "43_Modern--i96--25820",
      "imageFile": "43_Modern--i96--25820--a509f.jpg",
      "imageSize": [
        500,
        353
      ]
    },
    {
      "pdfName": "43_Modern",
      "pageNo": 97,
      "index": 97,
      "code": "25821",
      "id": "43_Modern--i97--25821",
      "imageFile": "43_Modern--i97--25821--f63b9.jpg",
      "imageSize": [
        500,
        353
      ]
    },
    {
      "pdfName": "43_Modern",
      "pageNo": 98,
      "index": 98,
      "code": "25822",
      "id": "43_Modern--i98--25822",
      "imageFile": "43_Modern--i98--25822--ecfe3.jpg",
      "imageSize": [
        500,
        353
      ]
    },
    {
      "pdfName": "43_Modern",
      "pageNo": 99,
      "index": 99,
      "code": "25823",
      "id": "43_Modern--i99--25823",
      "imageFile": "43_Modern--i99--25823--ddd21.jpg",
      "imageSize": [
        500,
        353
      ]
    },
    {
      "pdfName": "43_Modern",
      "pageNo": 100,
      "index": 100,
      "code": "25824",
      "id": "43_Modern--i100--25824",
      "imageFile": "43_Modern--i100--25824--6b805.jpg",
      "imageSize": [
        500,
        353
      ]
    },
    {
      "pdfName": "43_Modern",
      "pageNo": 101,
      "index": 101,
      "code": "25825",
      "id": "43_Modern--i101--25825",
      "imageFile": "43_Modern--i101--25825--67318.jpg",
      "imageSize": [
        500,
        353
      ]
    },
    {
      "pdfName": "43_Modern",
      "pageNo": 102,
      "index": 102,
      "code": "25826",
      "id": "43_Modern--i102--25826",
      "imageFile": "43_Modern--i102--25826--6abb3.jpg",
      "imageSize": [
        500,
        353
      ]
    },
    {
      "pdfName": "43_Modern",
      "pageNo": 103,
      "index": 103,
      "code": "25827",
      "id": "43_Modern--i103--25827",
      "imageFile": "43_Modern--i103--25827--6879b.jpg",
      "imageSize": [
        500,
        353
      ]
    },
    {
      "pdfName": "43_Modern",
      "pageNo": 104,
      "index": 104,
      "code": "25828",
      "id": "43_Modern--i104--25828",
      "imageFile": "43_Modern--i104--25828--de7da.jpg",
      "imageSize": [
        500,
        353
      ]
    },
    {
      "pdfName": "43_Modern",
      "pageNo": 105,
      "index": 105,
      "code": "25829",
      "id": "43_Modern--i105--25829",
      "imageFile": "43_Modern--i105--25829--509c1.jpg",
      "imageSize": [
        500,
        353
      ]
    },
    {
      "pdfName": "43_Modern",
      "pageNo": 106,
      "index": 106,
      "code": "25830",
      "id": "43_Modern--i106--25830",
      "imageFile": "43_Modern--i106--25830--3e95f.jpg",
      "imageSize": [
        500,
        353
      ]
    },
    {
      "pdfName": "43_Modern",
      "pageNo": 107,
      "index": 107,
      "code": "25831",
      "id": "43_Modern--i107--25831",
      "imageFile": "43_Modern--i107--25831--5b6c9.jpg",
      "imageSize": [
        500,
        353
      ]
    },
    {
      "pdfName": "43_Modern",
      "pageNo": 108,
      "index": 108,
      "code": "25832",
      "id": "43_Modern--i108--25832",
      "imageFile": "43_Modern--i108--25832--94bfe.jpg",
      "imageSize": [
        500,
        353
      ]
    },
    {
      "pdfName": "43_Modern",
      "pageNo": 109,
      "index": 109,
      "code": "25833",
      "id": "43_Modern--i109--25833",
      "imageFile": "43_Modern--i109--25833--0ae0f.jpg",
      "imageSize": [
        500,
        353
      ]
    },
    {
      "pdfName": "43_Modern",
      "pageNo": 110,
      "index": 110,
      "code": "25834",
      "id": "43_Modern--i110--25834",
      "imageFile": "43_Modern--i110--25834--05068.jpg",
      "imageSize": [
        500,
        353
      ]
    },
    {
      "pdfName": "43_Modern",
      "pageNo": 111,
      "index": 111,
      "code": "25835",
      "id": "43_Modern--i111--25835",
      "imageFile": "43_Modern--i111--25835--1c91e.jpg",
      "imageSize": [
        500,
        353
      ]
    },
    {
      "pdfName": "43_Modern",
      "pageNo": 112,
      "index": 112,
      "code": "25836",
      "id": "43_Modern--i112--25836",
      "imageFile": "43_Modern--i112--25836--b89aa.jpg",
      "imageSize": [
        500,
        353
      ]
    },
    {
      "pdfName": "43_Modern",
      "pageNo": 113,
      "index": 113,
      "code": "25837",
      "id": "43_Modern--i113--25837",
      "imageFile": "43_Modern--i113--25837--4c218.jpg",
      "imageSize": [
        500,
        353
      ]
    },
    {
      "pdfName": "43_Modern",
      "pageNo": 114,
      "index": 114,
      "code": "25838",
      "id": "43_Modern--i114--25838",
      "imageFile": "43_Modern--i114--25838--2d9da.jpg",
      "imageSize": [
        500,
        353
      ]
    },
    {
      "pdfName": "43_Modern",
      "pageNo": 115,
      "index": 115,
      "code": "25839",
      "id": "43_Modern--i115--25839",
      "imageFile": "43_Modern--i115--25839--304f7.jpg",
      "imageSize": [
        500,
        353
      ]
    },
    {
      "pdfName": "43_Modern",
      "pageNo": 116,
      "index": 116,
      "code": "25840",
      "id": "43_Modern--i116--25840",
      "imageFile": "43_Modern--i116--25840--4c86c.jpg",
      "imageSize": [
        500,
        353
      ]
    },
    {
      "pdfName": "43_Modern",
      "pageNo": 117,
      "index": 117,
      "code": "25841",
      "id": "43_Modern--i117--25841",
      "imageFile": "43_Modern--i117--25841--57522.jpg",
      "imageSize": [
        500,
        353
      ]
    },
    {
      "pdfName": "43_Modern",
      "pageNo": 118,
      "index": 118,
      "code": "25842",
      "id": "43_Modern--i118--25842",
      "imageFile": "43_Modern--i118--25842--bf818.jpg",
      "imageSize": [
        500,
        353
      ]
    },
    {
      "pdfName": "43_Modern",
      "pageNo": 119,
      "index": 119,
      "code": "25843",
      "id": "43_Modern--i119--25843",
      "imageFile": "43_Modern--i119--25843--88f87.jpg",
      "imageSize": [
        500,
        353
      ]
    },
    {
      "pdfName": "43_Modern",
      "pageNo": 120,
      "index": 120,
      "code": "25844",
      "id": "43_Modern--i120--25844",
      "imageFile": "43_Modern--i120--25844--bfa4f.jpg",
      "imageSize": [
        500,
        353
      ]
    },
    {
      "pdfName": "43_Modern",
      "pageNo": 121,
      "index": 121,
      "code": "25845",
      "id": "43_Modern--i121--25845",
      "imageFile": "43_Modern--i121--25845--dc9b4.jpg",
      "imageSize": [
        500,
        353
      ]
    },
    {
      "pdfName": "43_Modern",
      "pageNo": 122,
      "index": 122,
      "code": "25846",
      "id": "43_Modern--i122--25846",
      "imageFile": "43_Modern--i122--25846--97552.jpg",
      "imageSize": [
        500,
        353
      ]
    },
    {
      "pdfName": "43_Modern",
      "pageNo": 123,
      "index": 123,
      "code": "25847",
      "id": "43_Modern--i123--25847",
      "imageFile": "43_Modern--i123--25847--4cee8.jpg",
      "imageSize": [
        500,
        353
      ]
    },
    {
      "pdfName": "43_Modern",
      "pageNo": 124,
      "index": 124,
      "code": "25848",
      "id": "43_Modern--i124--25848",
      "imageFile": "43_Modern--i124--25848--8a652.jpg",
      "imageSize": [
        500,
        353
      ]
    },
    {
      "pdfName": "43_Modern",
      "pageNo": 125,
      "index": 125,
      "code": "25849",
      "id": "43_Modern--i125--25849",
      "imageFile": "43_Modern--i125--25849--37d2a.jpg",
      "imageSize": [
        500,
        353
      ]
    },
    {
      "pdfName": "43_Modern",
      "pageNo": 126,
      "index": 126,
      "code": "25850",
      "id": "43_Modern--i126--25850",
      "imageFile": "43_Modern--i126--25850--46a71.jpg",
      "imageSize": [
        500,
        353
      ]
    },
    {
      "pdfName": "43_Modern",
      "pageNo": 127,
      "index": 127,
      "code": "25851",
      "id": "43_Modern--i127--25851",
      "imageFile": "43_Modern--i127--25851--4903b.jpg",
      "imageSize": [
        500,
        353
      ]
    },
    {
      "pdfName": "43_Modern",
      "pageNo": 128,
      "index": 128,
      "code": "25852",
      "id": "43_Modern--i128--25852",
      "imageFile": "43_Modern--i128--25852--a84ca.jpg",
      "imageSize": [
        500,
        353
      ]
    },
    {
      "pdfName": "43_Modern",
      "pageNo": 129,
      "index": 129,
      "code": "25853",
      "id": "43_Modern--i129--25853",
      "imageFile": "43_Modern--i129--25853--18074.jpg",
      "imageSize": [
        500,
        353
      ]
    },
    {
      "pdfName": "43_Modern",
      "pageNo": 130,
      "index": 130,
      "code": "25854",
      "id": "43_Modern--i130--25854",
      "imageFile": "43_Modern--i130--25854--b005d.jpg",
      "imageSize": [
        500,
        353
      ]
    },
    {
      "pdfName": "43_Modern",
      "pageNo": 131,
      "index": 131,
      "code": "25855",
      "id": "43_Modern--i131--25855",
      "imageFile": "43_Modern--i131--25855--db593.jpg",
      "imageSize": [
        500,
        353
      ]
    },
    {
      "pdfName": "43_Modern",
      "pageNo": 132,
      "index": 132,
      "code": "25856",
      "id": "43_Modern--i132--25856",
      "imageFile": "43_Modern--i132--25856--1dce5.jpg",
      "imageSize": [
        500,
        353
      ]
    },
    {
      "pdfName": "43_Modern",
      "pageNo": 133,
      "index": 133,
      "code": "25857",
      "id": "43_Modern--i133--25857",
      "imageFile": "43_Modern--i133--25857--da0ee.jpg",
      "imageSize": [
        500,
        353
      ]
    },
    {
      "pdfName": "43_Modern",
      "pageNo": 134,
      "index": 134,
      "code": "25858",
      "id": "43_Modern--i134--25858",
      "imageFile": "43_Modern--i134--25858--440ba.jpg",
      "imageSize": [
        500,
        353
      ]
    },
    {
      "pdfName": "43_Modern",
      "pageNo": 135,
      "index": 135,
      "code": "25859",
      "id": "43_Modern--i135--25859",
      "imageFile": "43_Modern--i135--25859--d6a8c.jpg",
      "imageSize": [
        500,
        353
      ]
    },
    {
      "pdfName": "43_Modern",
      "pageNo": 136,
      "index": 136,
      "code": "25860",
      "id": "43_Modern--i136--25860",
      "imageFile": "43_Modern--i136--25860--ae8e2.jpg",
      "imageSize": [
        500,
        353
      ]
    },
    {
      "pdfName": "43_Modern",
      "pageNo": 137,
      "index": 137,
      "code": "25861",
      "id": "43_Modern--i137--25861",
      "imageFile": "43_Modern--i137--25861--89a17.jpg",
      "imageSize": [
        500,
        353
      ]
    },
    {
      "pdfName": "43_Modern",
      "pageNo": 138,
      "index": 138,
      "code": "25862",
      "id": "43_Modern--i138--25862",
      "imageFile": "43_Modern--i138--25862--b6343.jpg",
      "imageSize": [
        500,
        353
      ]
    },
    {
      "pdfName": "43_Modern",
      "pageNo": 139,
      "index": 139,
      "code": "25863",
      "id": "43_Modern--i139--25863",
      "imageFile": "43_Modern--i139--25863--36d5d.jpg",
      "imageSize": [
        500,
        353
      ]
    },
    {
      "pdfName": "43_Modern",
      "pageNo": 140,
      "index": 140,
      "code": "25864",
      "id": "43_Modern--i140--25864",
      "imageFile": "43_Modern--i140--25864--048ca.jpg",
      "imageSize": [
        500,
        353
      ]
    },
    {
      "pdfName": "43_Modern",
      "pageNo": 141,
      "index": 141,
      "code": "25865",
      "id": "43_Modern--i141--25865",
      "imageFile": "43_Modern--i141--25865--7dde4.jpg",
      "imageSize": [
        500,
        353
      ]
    },
    {
      "pdfName": "43_Modern",
      "pageNo": 142,
      "index": 142,
      "code": "25866",
      "id": "43_Modern--i142--25866",
      "imageFile": "43_Modern--i142--25866--3253b.jpg",
      "imageSize": [
        500,
        353
      ]
    },
    {
      "pdfName": "43_Modern",
      "pageNo": 143,
      "index": 143,
      "code": "25867",
      "id": "43_Modern--i143--25867",
      "imageFile": "43_Modern--i143--25867--6d57b.jpg",
      "imageSize": [
        500,
        353
      ]
    },
    {
      "pdfName": "43_Modern",
      "pageNo": 144,
      "index": 144,
      "code": "25868",
      "id": "43_Modern--i144--25868",
      "imageFile": "43_Modern--i144--25868--9aa62.jpg",
      "imageSize": [
        500,
        353
      ]
    },
    {
      "pdfName": "43_Modern",
      "pageNo": 145,
      "index": 145,
      "code": "25869",
      "id": "43_Modern--i145--25869",
      "imageFile": "43_Modern--i145--25869--a25d1.jpg",
      "imageSize": [
        500,
        353
      ]
    },
    {
      "pdfName": "43_Modern",
      "pageNo": 146,
      "index": 146,
      "code": "25870",
      "id": "43_Modern--i146--25870",
      "imageFile": "43_Modern--i146--25870--7235a.jpg",
      "imageSize": [
        500,
        353
      ]
    },
    {
      "pdfName": "43_Modern",
      "pageNo": 147,
      "index": 147,
      "code": "25871",
      "id": "43_Modern--i147--25871",
      "imageFile": "43_Modern--i147--25871--d46b3.jpg",
      "imageSize": [
        500,
        353
      ]
    },
    {
      "pdfName": "43_Modern",
      "pageNo": 148,
      "index": 148,
      "code": "25872",
      "id": "43_Modern--i148--25872",
      "imageFile": "43_Modern--i148--25872--d4a70.jpg",
      "imageSize": [
        500,
        353
      ]
    },
    {
      "pdfName": "43_Modern",
      "pageNo": 149,
      "index": 149,
      "code": "25873",
      "id": "43_Modern--i149--25873",
      "imageFile": "43_Modern--i149--25873--63952.jpg",
      "imageSize": [
        500,
        353
      ]
    },
    {
      "pdfName": "43_Modern",
      "pageNo": 150,
      "index": 150,
      "code": "25874",
      "id": "43_Modern--i150--25874",
      "imageFile": "43_Modern--i150--25874--62d3b.jpg",
      "imageSize": [
        500,
        353
      ]
    },
    {
      "pdfName": "43_Modern",
      "pageNo": 151,
      "index": 151,
      "code": "25875",
      "id": "43_Modern--i151--25875",
      "imageFile": "43_Modern--i151--25875--efb54.jpg",
      "imageSize": [
        500,
        353
      ]
    },
    {
      "pdfName": "43_Modern",
      "pageNo": 152,
      "index": 152,
      "code": "25876",
      "id": "43_Modern--i152--25876",
      "imageFile": "43_Modern--i152--25876--8e804.jpg",
      "imageSize": [
        500,
        353
      ]
    },
    {
      "pdfName": "43_Modern",
      "pageNo": 153,
      "index": 153,
      "code": "25877",
      "id": "43_Modern--i153--25877",
      "imageFile": "43_Modern--i153--25877--2b5f6.jpg",
      "imageSize": [
        500,
        353
      ]
    },
    {
      "pdfName": "43_Modern",
      "pageNo": 154,
      "index": 154,
      "code": "25878",
      "id": "43_Modern--i154--25878",
      "imageFile": "43_Modern--i154--25878--16a89.jpg",
      "imageSize": [
        500,
        353
      ]
    },
    {
      "pdfName": "43_Modern",
      "pageNo": 155,
      "index": 155,
      "code": "25879",
      "id": "43_Modern--i155--25879",
      "imageFile": "43_Modern--i155--25879--ce4bb.jpg",
      "imageSize": [
        500,
        353
      ]
    },
    {
      "pdfName": "43_Modern",
      "pageNo": 156,
      "index": 156,
      "code": "25880",
      "id": "43_Modern--i156--25880",
      "imageFile": "43_Modern--i156--25880--4aac0.jpg",
      "imageSize": [
        500,
        353
      ]
    },
    {
      "pdfName": "43_Modern",
      "pageNo": 157,
      "index": 157,
      "code": "25881",
      "id": "43_Modern--i157--25881",
      "imageFile": "43_Modern--i157--25881--ed97b.jpg",
      "imageSize": [
        500,
        353
      ]
    },
    {
      "pdfName": "43_Modern",
      "pageNo": 158,
      "index": 158,
      "code": "25882",
      "id": "43_Modern--i158--25882",
      "imageFile": "43_Modern--i158--25882--e364f.jpg",
      "imageSize": [
        500,
        353
      ]
    },
    {
      "pdfName": "43_Modern",
      "pageNo": 159,
      "index": 159,
      "code": "25883",
      "id": "43_Modern--i159--25883",
      "imageFile": "43_Modern--i159--25883--70d80.jpg",
      "imageSize": [
        500,
        353
      ]
    },
    {
      "pdfName": "43_Modern",
      "pageNo": 160,
      "index": 160,
      "code": "25884",
      "id": "43_Modern--i160--25884",
      "imageFile": "43_Modern--i160--25884--620ff.jpg",
      "imageSize": [
        500,
        353
      ]
    },
    {
      "pdfName": "43_Modern",
      "pageNo": 161,
      "index": 161,
      "code": "25885",
      "id": "43_Modern--i161--25885",
      "imageFile": "43_Modern--i161--25885--299f6.jpg",
      "imageSize": [
        500,
        353
      ]
    },
    {
      "pdfName": "43_Modern",
      "pageNo": 162,
      "index": 162,
      "code": "25886",
      "id": "43_Modern--i162--25886",
      "imageFile": "43_Modern--i162--25886--582cb.jpg",
      "imageSize": [
        500,
        353
      ]
    },
    {
      "pdfName": "43_Modern",
      "pageNo": 163,
      "index": 163,
      "code": "25887",
      "id": "43_Modern--i163--25887",
      "imageFile": "43_Modern--i163--25887--e20fb.jpg",
      "imageSize": [
        500,
        353
      ]
    },
    {
      "pdfName": "43_Modern",
      "pageNo": 164,
      "index": 164,
      "code": "25888",
      "id": "43_Modern--i164--25888",
      "imageFile": "43_Modern--i164--25888--7d2b6.jpg",
      "imageSize": [
        500,
        353
      ]
    },
    {
      "pdfName": "43_Modern",
      "pageNo": 165,
      "index": 165,
      "code": "25889",
      "id": "43_Modern--i165--25889",
      "imageFile": "43_Modern--i165--25889--e28a2.jpg",
      "imageSize": [
        500,
        353
      ]
    },
    {
      "pdfName": "43_Modern",
      "pageNo": 166,
      "index": 166,
      "code": "25890",
      "id": "43_Modern--i166--25890",
      "imageFile": "43_Modern--i166--25890--402b0.jpg",
      "imageSize": [
        500,
        353
      ]
    },
    {
      "pdfName": "43_Modern",
      "pageNo": 167,
      "index": 167,
      "code": "25891",
      "id": "43_Modern--i167--25891",
      "imageFile": "43_Modern--i167--25891--3330a.jpg",
      "imageSize": [
        500,
        353
      ]
    },
    {
      "pdfName": "43_Modern",
      "pageNo": 168,
      "index": 168,
      "code": "25892",
      "id": "43_Modern--i168--25892",
      "imageFile": "43_Modern--i168--25892--81c7e.jpg",
      "imageSize": [
        500,
        353
      ]
    },
    {
      "pdfName": "43_Modern",
      "pageNo": 169,
      "index": 169,
      "code": "25893",
      "id": "43_Modern--i169--25893",
      "imageFile": "43_Modern--i169--25893--69937.jpg",
      "imageSize": [
        500,
        353
      ]
    },
    {
      "pdfName": "43_Modern",
      "pageNo": 170,
      "index": 170,
      "code": "25894",
      "id": "43_Modern--i170--25894",
      "imageFile": "43_Modern--i170--25894--37e26.jpg",
      "imageSize": [
        500,
        353
      ]
    },
    {
      "pdfName": "43_Modern",
      "pageNo": 171,
      "index": 171,
      "code": "25895",
      "id": "43_Modern--i171--25895",
      "imageFile": "43_Modern--i171--25895--04cda.jpg",
      "imageSize": [
        500,
        353
      ]
    },
    {
      "pdfName": "43_Modern",
      "pageNo": 172,
      "index": 172,
      "code": "25896",
      "id": "43_Modern--i172--25896",
      "imageFile": "43_Modern--i172--25896--df55c.jpg",
      "imageSize": [
        500,
        353
      ]
    },
    {
      "pdfName": "43_Modern",
      "pageNo": 173,
      "index": 173,
      "code": "25897",
      "id": "43_Modern--i173--25897",
      "imageFile": "43_Modern--i173--25897--d16ba.jpg",
      "imageSize": [
        500,
        353
      ]
    },
    {
      "pdfName": "43_Modern",
      "pageNo": 174,
      "index": 174,
      "code": "25898",
      "id": "43_Modern--i174--25898",
      "imageFile": "43_Modern--i174--25898--f184b.jpg",
      "imageSize": [
        500,
        353
      ]
    },
    {
      "pdfName": "43_Modern",
      "pageNo": 175,
      "index": 175,
      "code": "25899",
      "id": "43_Modern--i175--25899",
      "imageFile": "43_Modern--i175--25899--35208.jpg",
      "imageSize": [
        500,
        353
      ]
    },
    {
      "pdfName": "43_Modern",
      "pageNo": 176,
      "index": 176,
      "code": "25900",
      "id": "43_Modern--i176--25900",
      "imageFile": "43_Modern--i176--25900--de694.jpg",
      "imageSize": [
        500,
        353
      ]
    },
    {
      "pdfName": "43_Modern",
      "pageNo": 177,
      "index": 177,
      "code": "25901",
      "id": "43_Modern--i177--25901",
      "imageFile": "43_Modern--i177--25901--51c29.jpg",
      "imageSize": [
        500,
        353
      ]
    },
    {
      "pdfName": "43_Modern",
      "pageNo": 178,
      "index": 178,
      "code": "25902",
      "id": "43_Modern--i178--25902",
      "imageFile": "43_Modern--i178--25902--0b765.jpg",
      "imageSize": [
        500,
        353
      ]
    },
    {
      "pdfName": "43_Modern",
      "pageNo": 179,
      "index": 179,
      "code": "25903",
      "id": "43_Modern--i179--25903",
      "imageFile": "43_Modern--i179--25903--6355a.jpg",
      "imageSize": [
        500,
        353
      ]
    },
    {
      "pdfName": "43_Modern",
      "pageNo": 180,
      "index": 180,
      "code": "25904",
      "id": "43_Modern--i180--25904",
      "imageFile": "43_Modern--i180--25904--bcfdc.jpg",
      "imageSize": [
        500,
        353
      ]
    },
    {
      "pdfName": "43_Modern",
      "pageNo": 181,
      "index": 181,
      "code": "25905",
      "id": "43_Modern--i181--25905",
      "imageFile": "43_Modern--i181--25905--49049.jpg",
      "imageSize": [
        500,
        353
      ]
    },
    {
      "pdfName": "43_Modern",
      "pageNo": 182,
      "index": 182,
      "code": "25906",
      "id": "43_Modern--i182--25906",
      "imageFile": "43_Modern--i182--25906--1c42a.jpg",
      "imageSize": [
        500,
        353
      ]
    },
    {
      "pdfName": "43_Modern",
      "pageNo": 183,
      "index": 183,
      "code": "25907",
      "id": "43_Modern--i183--25907",
      "imageFile": "43_Modern--i183--25907--9502c.jpg",
      "imageSize": [
        500,
        353
      ]
    },
    {
      "pdfName": "43_Modern",
      "pageNo": 184,
      "index": 184,
      "code": "25908",
      "id": "43_Modern--i184--25908",
      "imageFile": "43_Modern--i184--25908--ffd4e.jpg",
      "imageSize": [
        500,
        353
      ]
    },
    {
      "pdfName": "43_Modern",
      "pageNo": 185,
      "index": 185,
      "code": "25909",
      "id": "43_Modern--i185--25909",
      "imageFile": "43_Modern--i185--25909--02bc4.jpg",
      "imageSize": [
        500,
        353
      ]
    },
    {
      "pdfName": "43_Modern",
      "pageNo": 186,
      "index": 186,
      "code": "25910",
      "id": "43_Modern--i186--25910",
      "imageFile": "43_Modern--i186--25910--fda61.jpg",
      "imageSize": [
        500,
        353
      ]
    },
    {
      "pdfName": "43_Modern",
      "pageNo": 187,
      "index": 187,
      "code": "25911",
      "id": "43_Modern--i187--25911",
      "imageFile": "43_Modern--i187--25911--b6f13.jpg",
      "imageSize": [
        500,
        353
      ]
    },
    {
      "pdfName": "43_Modern",
      "pageNo": 188,
      "index": 188,
      "code": "25912",
      "id": "43_Modern--i188--25912",
      "imageFile": "43_Modern--i188--25912--12e68.jpg",
      "imageSize": [
        500,
        353
      ]
    },
    {
      "pdfName": "43_Modern",
      "pageNo": 189,
      "index": 189,
      "code": "25913",
      "id": "43_Modern--i189--25913",
      "imageFile": "43_Modern--i189--25913--a79f4.jpg",
      "imageSize": [
        500,
        353
      ]
    },
    {
      "pdfName": "43_Modern",
      "pageNo": 190,
      "index": 190,
      "code": "25914",
      "id": "43_Modern--i190--25914",
      "imageFile": "43_Modern--i190--25914--ab449.jpg",
      "imageSize": [
        500,
        353
      ]
    },
    {
      "pdfName": "43_Modern",
      "pageNo": 191,
      "index": 191,
      "code": "25915",
      "id": "43_Modern--i191--25915",
      "imageFile": "43_Modern--i191--25915--2fe44.jpg",
      "imageSize": [
        500,
        353
      ]
    },
    {
      "pdfName": "43_Modern",
      "pageNo": 192,
      "index": 192,
      "code": "25916",
      "id": "43_Modern--i192--25916",
      "imageFile": "43_Modern--i192--25916--176aa.jpg",
      "imageSize": [
        500,
        353
      ]
    },
    {
      "pdfName": "43_Modern",
      "pageNo": 193,
      "index": 193,
      "code": "25917",
      "id": "43_Modern--i193--25917",
      "imageFile": "43_Modern--i193--25917--f6368.jpg",
      "imageSize": [
        500,
        353
      ]
    },
    {
      "pdfName": "43_Modern",
      "pageNo": 194,
      "index": 194,
      "code": "25918",
      "id": "43_Modern--i194--25918",
      "imageFile": "43_Modern--i194--25918--4bcb5.jpg",
      "imageSize": [
        500,
        353
      ]
    },
    {
      "pdfName": "43_Modern",
      "pageNo": 195,
      "index": 195,
      "code": "25919",
      "id": "43_Modern--i195--25919",
      "imageFile": "43_Modern--i195--25919--ed33a.jpg",
      "imageSize": [
        500,
        353
      ]
    },
    {
      "pdfName": "43_Modern",
      "pageNo": 196,
      "index": 196,
      "code": "25920",
      "id": "43_Modern--i196--25920",
      "imageFile": "43_Modern--i196--25920--b6bd5.jpg",
      "imageSize": [
        500,
        353
      ]
    },
    {
      "pdfName": "43_Modern",
      "pageNo": 197,
      "index": 197,
      "code": "25921",
      "id": "43_Modern--i197--25921",
      "imageFile": "43_Modern--i197--25921--eebbf.jpg",
      "imageSize": [
        500,
        353
      ]
    },
    {
      "pdfName": "43_Modern",
      "pageNo": 198,
      "index": 198,
      "code": "25922",
      "id": "43_Modern--i198--25922",
      "imageFile": "43_Modern--i198--25922--3e374.jpg",
      "imageSize": [
        500,
        353
      ]
    },
    {
      "pdfName": "43_Modern",
      "pageNo": 199,
      "index": 199,
      "code": "25923",
      "id": "43_Modern--i199--25923",
      "imageFile": "43_Modern--i199--25923--319ba.jpg",
      "imageSize": [
        500,
        353
      ]
    },
    {
      "pdfName": "43_Modern",
      "pageNo": 200,
      "index": 200,
      "code": "25924",
      "id": "43_Modern--i200--25924",
      "imageFile": "43_Modern--i200--25924--03923.jpg",
      "imageSize": [
        500,
        353
      ]
    },
    {
      "pdfName": "43_Modern",
      "pageNo": 201,
      "index": 201,
      "code": "25925",
      "id": "43_Modern--i201--25925",
      "imageFile": "43_Modern--i201--25925--51583.jpg",
      "imageSize": [
        500,
        353
      ]
    },
    {
      "pdfName": "43_Modern",
      "pageNo": 202,
      "index": 202,
      "code": "25926",
      "id": "43_Modern--i202--25926",
      "imageFile": "43_Modern--i202--25926--8e0d2.jpg",
      "imageSize": [
        500,
        353
      ]
    },
    {
      "pdfName": "43_Modern",
      "pageNo": 203,
      "index": 203,
      "code": "25927",
      "id": "43_Modern--i203--25927",
      "imageFile": "43_Modern--i203--25927--6efce.jpg",
      "imageSize": [
        500,
        353
      ]
    },
    {
      "pdfName": "43_Modern",
      "pageNo": 204,
      "index": 204,
      "code": "25928",
      "id": "43_Modern--i204--25928",
      "imageFile": "43_Modern--i204--25928--babcd.jpg",
      "imageSize": [
        500,
        353
      ]
    },
    {
      "pdfName": "43_Modern",
      "pageNo": 205,
      "index": 205,
      "code": "25929",
      "id": "43_Modern--i205--25929",
      "imageFile": "43_Modern--i205--25929--bddd9.jpg",
      "imageSize": [
        500,
        353
      ]
    },
    {
      "pdfName": "43_Modern",
      "pageNo": 206,
      "index": 206,
      "code": "25930",
      "id": "43_Modern--i206--25930",
      "imageFile": "43_Modern--i206--25930--b788a.jpg",
      "imageSize": [
        500,
        353
      ]
    },
    {
      "pdfName": "43_Modern",
      "pageNo": 207,
      "index": 207,
      "code": "25931",
      "id": "43_Modern--i207--25931",
      "imageFile": "43_Modern--i207--25931--c163c.jpg",
      "imageSize": [
        500,
        353
      ]
    },
    {
      "pdfName": "43_Modern",
      "pageNo": 208,
      "index": 208,
      "code": "25932",
      "id": "43_Modern--i208--25932",
      "imageFile": "43_Modern--i208--25932--97de0.jpg",
      "imageSize": [
        500,
        353
      ]
    },
    {
      "pdfName": "43_Modern",
      "pageNo": 209,
      "index": 209,
      "code": "25933",
      "id": "43_Modern--i209--25933",
      "imageFile": "43_Modern--i209--25933--e4fd1.jpg",
      "imageSize": [
        500,
        353
      ]
    },
    {
      "pdfName": "43_Modern",
      "pageNo": 210,
      "index": 210,
      "code": "25934",
      "id": "43_Modern--i210--25934",
      "imageFile": "43_Modern--i210--25934--83d2b.jpg",
      "imageSize": [
        500,
        353
      ]
    },
    {
      "pdfName": "43_Modern",
      "pageNo": 211,
      "index": 211,
      "code": "25935",
      "id": "43_Modern--i211--25935",
      "imageFile": "43_Modern--i211--25935--d888c.jpg",
      "imageSize": [
        500,
        353
      ]
    },
    {
      "pdfName": "43_Modern",
      "pageNo": 212,
      "index": 212,
      "code": "25936",
      "id": "43_Modern--i212--25936",
      "imageFile": "43_Modern--i212--25936--de4cd.jpg",
      "imageSize": [
        500,
        353
      ]
    },
    {
      "pdfName": "43_Modern",
      "pageNo": 213,
      "index": 213,
      "code": "25937",
      "id": "43_Modern--i213--25937",
      "imageFile": "43_Modern--i213--25937--6bca7.jpg",
      "imageSize": [
        500,
        353
      ]
    },
    {
      "pdfName": "43_Modern",
      "pageNo": 214,
      "index": 214,
      "code": "25938",
      "id": "43_Modern--i214--25938",
      "imageFile": "43_Modern--i214--25938--53491.jpg",
      "imageSize": [
        500,
        353
      ]
    },
    {
      "pdfName": "43_Modern",
      "pageNo": 215,
      "index": 215,
      "code": "25939",
      "id": "43_Modern--i215--25939",
      "imageFile": "43_Modern--i215--25939--5e59f.jpg",
      "imageSize": [
        500,
        353
      ]
    },
    {
      "pdfName": "43_Modern",
      "pageNo": 216,
      "index": 216,
      "code": "25940",
      "id": "43_Modern--i216--25940",
      "imageFile": "43_Modern--i216--25940--eade6.jpg",
      "imageSize": [
        500,
        353
      ]
    },
    {
      "pdfName": "43_Modern",
      "pageNo": 217,
      "index": 217,
      "code": "25941",
      "id": "43_Modern--i217--25941",
      "imageFile": "43_Modern--i217--25941--5b9c0.jpg",
      "imageSize": [
        500,
        353
      ]
    },
    {
      "pdfName": "43_Modern",
      "pageNo": 218,
      "index": 218,
      "code": "25942",
      "id": "43_Modern--i218--25942",
      "imageFile": "43_Modern--i218--25942--2cc6a.jpg",
      "imageSize": [
        500,
        353
      ]
    },
    {
      "pdfName": "43_Modern",
      "pageNo": 219,
      "index": 219,
      "code": "25943",
      "id": "43_Modern--i219--25943",
      "imageFile": "43_Modern--i219--25943--b874e.jpg",
      "imageSize": [
        500,
        353
      ]
    },
    {
      "pdfName": "43_Modern",
      "pageNo": 220,
      "index": 220,
      "code": "25944",
      "id": "43_Modern--i220--25944",
      "imageFile": "43_Modern--i220--25944--7c448.jpg",
      "imageSize": [
        500,
        353
      ]
    },
    {
      "pdfName": "43_Modern",
      "pageNo": 221,
      "index": 221,
      "code": "25945",
      "id": "43_Modern--i221--25945",
      "imageFile": "43_Modern--i221--25945--3e13d.jpg",
      "imageSize": [
        500,
        353
      ]
    },
    {
      "pdfName": "43_Modern",
      "pageNo": 222,
      "index": 222,
      "code": "25946",
      "id": "43_Modern--i222--25946",
      "imageFile": "43_Modern--i222--25946--0f42c.jpg",
      "imageSize": [
        500,
        353
      ]
    },
    {
      "pdfName": "43_Modern",
      "pageNo": 223,
      "index": 223,
      "code": "25947",
      "id": "43_Modern--i223--25947",
      "imageFile": "43_Modern--i223--25947--fb04b.jpg",
      "imageSize": [
        500,
        353
      ]
    },
    {
      "pdfName": "43_Modern",
      "pageNo": 224,
      "index": 224,
      "code": "25948",
      "id": "43_Modern--i224--25948",
      "imageFile": "43_Modern--i224--25948--e7b6a.jpg",
      "imageSize": [
        500,
        353
      ]
    },
    {
      "pdfName": "43_Modern",
      "pageNo": 225,
      "index": 225,
      "code": "25949",
      "id": "43_Modern--i225--25949",
      "imageFile": "43_Modern--i225--25949--5adeb.jpg",
      "imageSize": [
        500,
        353
      ]
    },
    {
      "pdfName": "43_Modern",
      "pageNo": 226,
      "index": 226,
      "code": "25950",
      "id": "43_Modern--i226--25950",
      "imageFile": "43_Modern--i226--25950--12f65.jpg",
      "imageSize": [
        500,
        353
      ]
    },
    {
      "pdfName": "43_Modern",
      "pageNo": 227,
      "index": 227,
      "code": "25951",
      "id": "43_Modern--i227--25951",
      "imageFile": "43_Modern--i227--25951--45f36.jpg",
      "imageSize": [
        500,
        353
      ]
    },
    {
      "pdfName": "43_Modern",
      "pageNo": 228,
      "index": 228,
      "code": "25952",
      "id": "43_Modern--i228--25952",
      "imageFile": "43_Modern--i228--25952--b85fd.jpg",
      "imageSize": [
        500,
        353
      ]
    },
    {
      "pdfName": "43_Modern",
      "pageNo": 229,
      "index": 229,
      "code": "25953",
      "id": "43_Modern--i229--25953",
      "imageFile": "43_Modern--i229--25953--7272a.jpg",
      "imageSize": [
        500,
        353
      ]
    },
    {
      "pdfName": "43_Modern",
      "pageNo": 230,
      "index": 230,
      "code": "25954",
      "id": "43_Modern--i230--25954",
      "imageFile": "43_Modern--i230--25954--02db1.jpg",
      "imageSize": [
        500,
        353
      ]
    },
    {
      "pdfName": "43_Modern",
      "pageNo": 231,
      "index": 231,
      "code": "25955",
      "id": "43_Modern--i231--25955",
      "imageFile": "43_Modern--i231--25955--39a79.jpg",
      "imageSize": [
        500,
        353
      ]
    },
    {
      "pdfName": "43_Modern",
      "pageNo": 232,
      "index": 232,
      "code": "25956",
      "id": "43_Modern--i232--25956",
      "imageFile": "43_Modern--i232--25956--0e533.jpg",
      "imageSize": [
        500,
        353
      ]
    },
    {
      "pdfName": "43_Modern",
      "pageNo": 233,
      "index": 233,
      "code": "25957",
      "id": "43_Modern--i233--25957",
      "imageFile": "43_Modern--i233--25957--f6ef4.jpg",
      "imageSize": [
        500,
        353
      ]
    },
    {
      "pdfName": "43_Modern",
      "pageNo": 234,
      "index": 234,
      "code": "25958",
      "id": "43_Modern--i234--25958",
      "imageFile": "43_Modern--i234--25958--b33d9.jpg",
      "imageSize": [
        500,
        353
      ]
    },
    {
      "pdfName": "43_Modern",
      "pageNo": 235,
      "index": 235,
      "code": "25959",
      "id": "43_Modern--i235--25959",
      "imageFile": "43_Modern--i235--25959--e75bf.jpg",
      "imageSize": [
        500,
        353
      ]
    },
    {
      "pdfName": "43_Modern",
      "pageNo": 236,
      "index": 236,
      "code": "25960",
      "id": "43_Modern--i236--25960",
      "imageFile": "43_Modern--i236--25960--360db.jpg",
      "imageSize": [
        500,
        353
      ]
    },
    {
      "pdfName": "43_Modern",
      "pageNo": 237,
      "index": 237,
      "code": "25961",
      "id": "43_Modern--i237--25961",
      "imageFile": "43_Modern--i237--25961--19260.jpg",
      "imageSize": [
        500,
        353
      ]
    },
    {
      "pdfName": "43_Modern",
      "pageNo": 238,
      "index": 238,
      "code": "25962",
      "id": "43_Modern--i238--25962",
      "imageFile": "43_Modern--i238--25962--81010.jpg",
      "imageSize": [
        500,
        353
      ]
    },
    {
      "pdfName": "43_Modern",
      "pageNo": 239,
      "index": 239,
      "code": "25963",
      "id": "43_Modern--i239--25963",
      "imageFile": "43_Modern--i239--25963--7260a.jpg",
      "imageSize": [
        500,
        353
      ]
    },
    {
      "pdfName": "43_Modern",
      "pageNo": 240,
      "index": 240,
      "code": "25964",
      "id": "43_Modern--i240--25964",
      "imageFile": "43_Modern--i240--25964--716b8.jpg",
      "imageSize": [
        500,
        353
      ]
    },
    {
      "pdfName": "43_Modern",
      "pageNo": 241,
      "index": 241,
      "code": "25965",
      "id": "43_Modern--i241--25965",
      "imageFile": "43_Modern--i241--25965--d7048.jpg",
      "imageSize": [
        500,
        353
      ]
    },
    {
      "pdfName": "43_Modern",
      "pageNo": 242,
      "index": 242,
      "code": "25966",
      "id": "43_Modern--i242--25966",
      "imageFile": "43_Modern--i242--25966--98547.jpg",
      "imageSize": [
        500,
        353
      ]
    },
    {
      "pdfName": "43_Modern",
      "pageNo": 243,
      "index": 243,
      "code": "25967",
      "id": "43_Modern--i243--25967",
      "imageFile": "43_Modern--i243--25967--13562.jpg",
      "imageSize": [
        500,
        353
      ]
    },
    {
      "pdfName": "43_Modern",
      "pageNo": 244,
      "index": 244,
      "code": "25968",
      "id": "43_Modern--i244--25968",
      "imageFile": "43_Modern--i244--25968--34be8.jpg",
      "imageSize": [
        500,
        353
      ]
    },
    {
      "pdfName": "43_Modern",
      "pageNo": 245,
      "index": 245,
      "code": "25969",
      "id": "43_Modern--i245--25969",
      "imageFile": "43_Modern--i245--25969--be91d.jpg",
      "imageSize": [
        500,
        353
      ]
    },
    {
      "pdfName": "43_Modern",
      "pageNo": 246,
      "index": 246,
      "code": "25970",
      "id": "43_Modern--i246--25970",
      "imageFile": "43_Modern--i246--25970--4b855.jpg",
      "imageSize": [
        500,
        353
      ]
    },
    {
      "pdfName": "43_Modern",
      "pageNo": 247,
      "index": 247,
      "code": "25971",
      "id": "43_Modern--i247--25971",
      "imageFile": "43_Modern--i247--25971--0708a.jpg",
      "imageSize": [
        500,
        353
      ]
    },
    {
      "pdfName": "43_Modern",
      "pageNo": 248,
      "index": 248,
      "code": "25972",
      "id": "43_Modern--i248--25972",
      "imageFile": "43_Modern--i248--25972--99497.jpg",
      "imageSize": [
        500,
        353
      ]
    },
    {
      "pdfName": "43_Modern",
      "pageNo": 249,
      "index": 249,
      "code": "25973",
      "id": "43_Modern--i249--25973",
      "imageFile": "43_Modern--i249--25973--fd511.jpg",
      "imageSize": [
        500,
        353
      ]
    },
    {
      "pdfName": "43_Modern",
      "pageNo": 250,
      "index": 250,
      "code": "25974",
      "id": "43_Modern--i250--25974",
      "imageFile": "43_Modern--i250--25974--11d8d.jpg",
      "imageSize": [
        500,
        353
      ]
    },
    {
      "pdfName": "43_Modern",
      "pageNo": 251,
      "index": 251,
      "code": "25975",
      "id": "43_Modern--i251--25975",
      "imageFile": "43_Modern--i251--25975--a9829.jpg",
      "imageSize": [
        500,
        353
      ]
    },
    {
      "pdfName": "43_Modern",
      "pageNo": 252,
      "index": 252,
      "code": "25976",
      "id": "43_Modern--i252--25976",
      "imageFile": "43_Modern--i252--25976--633e7.jpg",
      "imageSize": [
        500,
        353
      ]
    },
    {
      "pdfName": "43_Modern",
      "pageNo": 253,
      "index": 253,
      "code": "25977",
      "id": "43_Modern--i253--25977",
      "imageFile": "43_Modern--i253--25977--431a2.jpg",
      "imageSize": [
        500,
        353
      ]
    },
    {
      "pdfName": "43_Modern",
      "pageNo": 254,
      "index": 254,
      "code": "25978",
      "id": "43_Modern--i254--25978",
      "imageFile": "43_Modern--i254--25978--93df0.jpg",
      "imageSize": [
        500,
        353
      ]
    },
    {
      "pdfName": "43_Modern",
      "pageNo": 255,
      "index": 255,
      "code": "25979",
      "id": "43_Modern--i255--25979",
      "imageFile": "43_Modern--i255--25979--3ccfc.jpg",
      "imageSize": [
        500,
        353
      ]
    },
    {
      "pdfName": "43_Modern",
      "pageNo": 256,
      "index": 256,
      "code": "25980",
      "id": "43_Modern--i256--25980",
      "imageFile": "43_Modern--i256--25980--b1de5.jpg",
      "imageSize": [
        500,
        353
      ]
    },
    {
      "pdfName": "43_Modern",
      "pageNo": 257,
      "index": 257,
      "code": "25981",
      "id": "43_Modern--i257--25981",
      "imageFile": "43_Modern--i257--25981--4afa4.jpg",
      "imageSize": [
        500,
        353
      ]
    },
    {
      "pdfName": "43_Modern",
      "pageNo": 258,
      "index": 258,
      "code": "25982",
      "id": "43_Modern--i258--25982",
      "imageFile": "43_Modern--i258--25982--31ae7.jpg",
      "imageSize": [
        500,
        353
      ]
    },
    {
      "pdfName": "43_Modern",
      "pageNo": 259,
      "index": 259,
      "code": "25983",
      "id": "43_Modern--i259--25983",
      "imageFile": "43_Modern--i259--25983--3497f.jpg",
      "imageSize": [
        500,
        353
      ]
    },
    {
      "pdfName": "43_Modern",
      "pageNo": 260,
      "index": 260,
      "code": "25984",
      "id": "43_Modern--i260--25984",
      "imageFile": "43_Modern--i260--25984--4bce8.jpg",
      "imageSize": [
        500,
        353
      ]
    },
    {
      "pdfName": "43_Modern",
      "pageNo": 261,
      "index": 261,
      "code": "25985",
      "id": "43_Modern--i261--25985",
      "imageFile": "43_Modern--i261--25985--5c5d9.jpg",
      "imageSize": [
        500,
        353
      ]
    },
    {
      "pdfName": "43_Modern",
      "pageNo": 262,
      "index": 262,
      "code": "25986",
      "id": "43_Modern--i262--25986",
      "imageFile": "43_Modern--i262--25986--8c722.jpg",
      "imageSize": [
        500,
        353
      ]
    },
    {
      "pdfName": "43_Modern",
      "pageNo": 263,
      "index": 263,
      "code": "25987",
      "id": "43_Modern--i263--25987",
      "imageFile": "43_Modern--i263--25987--5b86d.jpg",
      "imageSize": [
        500,
        353
      ]
    },
    {
      "pdfName": "43_Modern",
      "pageNo": 264,
      "index": 264,
      "code": "25988",
      "id": "43_Modern--i264--25988",
      "imageFile": "43_Modern--i264--25988--645bc.jpg",
      "imageSize": [
        500,
        353
      ]
    },
    {
      "pdfName": "43_Modern",
      "pageNo": 265,
      "index": 265,
      "code": "25989",
      "id": "43_Modern--i265--25989",
      "imageFile": "43_Modern--i265--25989--b6ab0.jpg",
      "imageSize": [
        500,
        353
      ]
    },
    {
      "pdfName": "43_Modern",
      "pageNo": 266,
      "index": 266,
      "code": "25990",
      "id": "43_Modern--i266--25990",
      "imageFile": "43_Modern--i266--25990--f1158.jpg",
      "imageSize": [
        500,
        353
      ]
    },
    {
      "pdfName": "43_Modern",
      "pageNo": 267,
      "index": 267,
      "code": "25991",
      "id": "43_Modern--i267--25991",
      "imageFile": "43_Modern--i267--25991--10156.jpg",
      "imageSize": [
        500,
        353
      ]
    },
    {
      "pdfName": "43_Modern",
      "pageNo": 268,
      "index": 268,
      "code": "25992",
      "id": "43_Modern--i268--25992",
      "imageFile": "43_Modern--i268--25992--2a087.jpg",
      "imageSize": [
        500,
        353
      ]
    },
    {
      "pdfName": "43_Modern",
      "pageNo": 269,
      "index": 269,
      "code": "25993",
      "id": "43_Modern--i269--25993",
      "imageFile": "43_Modern--i269--25993--0cf55.jpg",
      "imageSize": [
        500,
        353
      ]
    },
    {
      "pdfName": "43_Modern",
      "pageNo": 270,
      "index": 270,
      "code": "25994",
      "id": "43_Modern--i270--25994",
      "imageFile": "43_Modern--i270--25994--8b5ec.jpg",
      "imageSize": [
        500,
        353
      ]
    },
    {
      "pdfName": "43_Modern",
      "pageNo": 271,
      "index": 271,
      "code": "25995",
      "id": "43_Modern--i271--25995",
      "imageFile": "43_Modern--i271--25995--a80f0.jpg",
      "imageSize": [
        500,
        353
      ]
    },
    {
      "pdfName": "43_Modern",
      "pageNo": 272,
      "index": 272,
      "code": "25996",
      "id": "43_Modern--i272--25996",
      "imageFile": "43_Modern--i272--25996--9e166.jpg",
      "imageSize": [
        500,
        353
      ]
    },
    {
      "pdfName": "43_Modern",
      "pageNo": 273,
      "index": 273,
      "code": "25997",
      "id": "43_Modern--i273--25997",
      "imageFile": "43_Modern--i273--25997--91997.jpg",
      "imageSize": [
        500,
        353
      ]
    },
    {
      "pdfName": "43_Modern",
      "pageNo": 274,
      "index": 274,
      "code": "25998",
      "id": "43_Modern--i274--25998",
      "imageFile": "43_Modern--i274--25998--a5c4c.jpg",
      "imageSize": [
        500,
        353
      ]
    },
    {
      "pdfName": "43_Modern",
      "pageNo": 275,
      "index": 275,
      "code": "25999",
      "id": "43_Modern--i275--25999",
      "imageFile": "43_Modern--i275--25999--93eb2.jpg",
      "imageSize": [
        500,
        353
      ]
    },
    {
      "pdfName": "43_Modern",
      "pageNo": 276,
      "index": 276,
      "code": "26000",
      "id": "43_Modern--i276--26000",
      "imageFile": "43_Modern--i276--26000--f204b.jpg",
      "imageSize": [
        500,
        353
      ]
    },
    {
      "pdfName": "43_Modern",
      "pageNo": 277,
      "index": 277,
      "code": "26001",
      "id": "43_Modern--i277--26001",
      "imageFile": "43_Modern--i277--26001--c5990.jpg",
      "imageSize": [
        500,
        353
      ]
    },
    {
      "pdfName": "43_Modern",
      "pageNo": 278,
      "index": 278,
      "code": "26002",
      "id": "43_Modern--i278--26002",
      "imageFile": "43_Modern--i278--26002--3035b.jpg",
      "imageSize": [
        500,
        353
      ]
    },
    {
      "pdfName": "43_Modern",
      "pageNo": 279,
      "index": 279,
      "code": "26003",
      "id": "43_Modern--i279--26003",
      "imageFile": "43_Modern--i279--26003--35321.jpg",
      "imageSize": [
        500,
        353
      ]
    },
    {
      "pdfName": "43_Modern",
      "pageNo": 280,
      "index": 280,
      "code": "26004",
      "id": "43_Modern--i280--26004",
      "imageFile": "43_Modern--i280--26004--ac03f.jpg",
      "imageSize": [
        500,
        353
      ]
    },
    {
      "pdfName": "43_Modern",
      "pageNo": 281,
      "index": 281,
      "code": "26005",
      "id": "43_Modern--i281--26005",
      "imageFile": "43_Modern--i281--26005--3ba4d.jpg",
      "imageSize": [
        500,
        353
      ]
    },
    {
      "pdfName": "43_Modern",
      "pageNo": 282,
      "index": 282,
      "code": "26006",
      "id": "43_Modern--i282--26006",
      "imageFile": "43_Modern--i282--26006--c5a3c.jpg",
      "imageSize": [
        500,
        353
      ]
    },
    {
      "pdfName": "43_Modern",
      "pageNo": 283,
      "index": 283,
      "code": "26007",
      "id": "43_Modern--i283--26007",
      "imageFile": "43_Modern--i283--26007--6674d.jpg",
      "imageSize": [
        500,
        353
      ]
    },
    {
      "pdfName": "43_Modern",
      "pageNo": 284,
      "index": 284,
      "code": "26008",
      "id": "43_Modern--i284--26008",
      "imageFile": "43_Modern--i284--26008--16142.jpg",
      "imageSize": [
        500,
        353
      ]
    },
    {
      "pdfName": "43_Modern",
      "pageNo": 285,
      "index": 285,
      "code": "26009",
      "id": "43_Modern--i285--26009",
      "imageFile": "43_Modern--i285--26009--b1805.jpg",
      "imageSize": [
        500,
        353
      ]
    },
    {
      "pdfName": "43_Modern",
      "pageNo": 286,
      "index": 286,
      "code": "26010",
      "id": "43_Modern--i286--26010",
      "imageFile": "43_Modern--i286--26010--42448.jpg",
      "imageSize": [
        500,
        353
      ]
    },
    {
      "pdfName": "43_Modern",
      "pageNo": 287,
      "index": 287,
      "code": "26011",
      "id": "43_Modern--i287--26011",
      "imageFile": "43_Modern--i287--26011--a7f56.jpg",
      "imageSize": [
        500,
        353
      ]
    },
    {
      "pdfName": "43_Modern",
      "pageNo": 288,
      "index": 288,
      "code": "26012",
      "id": "43_Modern--i288--26012",
      "imageFile": "43_Modern--i288--26012--6eae8.jpg",
      "imageSize": [
        500,
        353
      ]
    },
    {
      "pdfName": "43_Modern",
      "pageNo": 289,
      "index": 289,
      "code": "26013",
      "id": "43_Modern--i289--26013",
      "imageFile": "43_Modern--i289--26013--1017e.jpg",
      "imageSize": [
        500,
        353
      ]
    },
    {
      "pdfName": "43_Modern",
      "pageNo": 290,
      "index": 290,
      "code": "26014",
      "id": "43_Modern--i290--26014",
      "imageFile": "43_Modern--i290--26014--efaa2.jpg",
      "imageSize": [
        500,
        353
      ]
    },
    {
      "pdfName": "43_Modern",
      "pageNo": 291,
      "index": 291,
      "code": "26015",
      "id": "43_Modern--i291--26015",
      "imageFile": "43_Modern--i291--26015--8a53d.jpg",
      "imageSize": [
        500,
        353
      ]
    },
    {
      "pdfName": "43_Modern",
      "pageNo": 292,
      "index": 292,
      "code": "26016",
      "id": "43_Modern--i292--26016",
      "imageFile": "43_Modern--i292--26016--83b8c.jpg",
      "imageSize": [
        500,
        353
      ]
    },
    {
      "pdfName": "43_Modern",
      "pageNo": 293,
      "index": 293,
      "code": "26017",
      "id": "43_Modern--i293--26017",
      "imageFile": "43_Modern--i293--26017--94f29.jpg",
      "imageSize": [
        500,
        353
      ]
    },
    {
      "pdfName": "43_Modern",
      "pageNo": 294,
      "index": 294,
      "code": "26018",
      "id": "43_Modern--i294--26018",
      "imageFile": "43_Modern--i294--26018--3d713.jpg",
      "imageSize": [
        500,
        353
      ]
    },
    {
      "pdfName": "43_Modern",
      "pageNo": 295,
      "index": 295,
      "code": "26019",
      "id": "43_Modern--i295--26019",
      "imageFile": "43_Modern--i295--26019--32f6b.jpg",
      "imageSize": [
        500,
        353
      ]
    },
    {
      "pdfName": "43_Modern",
      "pageNo": 296,
      "index": 296,
      "code": "26020",
      "id": "43_Modern--i296--26020",
      "imageFile": "43_Modern--i296--26020--5cb6d.jpg",
      "imageSize": [
        500,
        353
      ]
    },
    {
      "pdfName": "43_Modern",
      "pageNo": 297,
      "index": 297,
      "code": "26021",
      "id": "43_Modern--i297--26021",
      "imageFile": "43_Modern--i297--26021--fdaaf.jpg",
      "imageSize": [
        500,
        353
      ]
    },
    {
      "pdfName": "43_Modern",
      "pageNo": 298,
      "index": 298,
      "code": "26022",
      "id": "43_Modern--i298--26022",
      "imageFile": "43_Modern--i298--26022--02d76.jpg",
      "imageSize": [
        500,
        353
      ]
    },
    {
      "pdfName": "43_Modern",
      "pageNo": 299,
      "index": 299,
      "code": "26023",
      "id": "43_Modern--i299--26023",
      "imageFile": "43_Modern--i299--26023--e16b5.jpg",
      "imageSize": [
        500,
        353
      ]
    },
    {
      "pdfName": "43_Modern",
      "pageNo": 300,
      "index": 300,
      "code": "26024",
      "id": "43_Modern--i300--26024",
      "imageFile": "43_Modern--i300--26024--ac716.jpg",
      "imageSize": [
        500,
        353
      ]
    },
    {
      "pdfName": "43_Modern",
      "pageNo": 301,
      "index": 301,
      "code": "26025",
      "id": "43_Modern--i301--26025",
      "imageFile": "43_Modern--i301--26025--4a87c.jpg",
      "imageSize": [
        500,
        353
      ]
    },
    {
      "pdfName": "43_Modern",
      "pageNo": 302,
      "index": 302,
      "code": "26026",
      "id": "43_Modern--i302--26026",
      "imageFile": "43_Modern--i302--26026--c13c3.jpg",
      "imageSize": [
        500,
        353
      ]
    },
    {
      "pdfName": "43_Modern",
      "pageNo": 303,
      "index": 303,
      "code": "26027",
      "id": "43_Modern--i303--26027",
      "imageFile": "43_Modern--i303--26027--a80ab.jpg",
      "imageSize": [
        500,
        353
      ]
    },
    {
      "pdfName": "43_Modern",
      "pageNo": 304,
      "index": 304,
      "code": "26028",
      "id": "43_Modern--i304--26028",
      "imageFile": "43_Modern--i304--26028--3426a.jpg",
      "imageSize": [
        500,
        353
      ]
    },
    {
      "pdfName": "43_Modern",
      "pageNo": 305,
      "index": 305,
      "code": "26029",
      "id": "43_Modern--i305--26029",
      "imageFile": "43_Modern--i305--26029--cd30f.jpg",
      "imageSize": [
        500,
        353
      ]
    },
    {
      "pdfName": "43_Modern",
      "pageNo": 306,
      "index": 306,
      "code": "26030",
      "id": "43_Modern--i306--26030",
      "imageFile": "43_Modern--i306--26030--2c528.jpg",
      "imageSize": [
        500,
        353
      ]
    },
    {
      "pdfName": "43_Modern",
      "pageNo": 307,
      "index": 307,
      "code": "26031",
      "id": "43_Modern--i307--26031",
      "imageFile": "43_Modern--i307--26031--68290.jpg",
      "imageSize": [
        500,
        353
      ]
    },
    {
      "pdfName": "43_Modern",
      "pageNo": 308,
      "index": 308,
      "code": "26032",
      "id": "43_Modern--i308--26032",
      "imageFile": "43_Modern--i308--26032--1b137.jpg",
      "imageSize": [
        500,
        353
      ]
    },
    {
      "pdfName": "43_Modern",
      "pageNo": 309,
      "index": 309,
      "code": "26033",
      "id": "43_Modern--i309--26033",
      "imageFile": "43_Modern--i309--26033--7cc0f.jpg",
      "imageSize": [
        500,
        353
      ]
    },
    {
      "pdfName": "43_Modern",
      "pageNo": 310,
      "index": 310,
      "code": "26034",
      "id": "43_Modern--i310--26034",
      "imageFile": "43_Modern--i310--26034--c834d.jpg",
      "imageSize": [
        500,
        353
      ]
    },
    {
      "pdfName": "43_Modern",
      "pageNo": 311,
      "index": 311,
      "code": "26035",
      "id": "43_Modern--i311--26035",
      "imageFile": "43_Modern--i311--26035--26757.jpg",
      "imageSize": [
        500,
        353
      ]
    },
    {
      "pdfName": "43_Modern",
      "pageNo": 312,
      "index": 312,
      "code": "26036",
      "id": "43_Modern--i312--26036",
      "imageFile": "43_Modern--i312--26036--a2fed.jpg",
      "imageSize": [
        500,
        353
      ]
    },
    {
      "pdfName": "43_Modern",
      "pageNo": 313,
      "index": 313,
      "code": "26037",
      "id": "43_Modern--i313--26037",
      "imageFile": "43_Modern--i313--26037--9045a.jpg",
      "imageSize": [
        500,
        353
      ]
    },
    {
      "pdfName": "43_Modern",
      "pageNo": 314,
      "index": 314,
      "code": "26038",
      "id": "43_Modern--i314--26038",
      "imageFile": "43_Modern--i314--26038--facdb.jpg",
      "imageSize": [
        500,
        353
      ]
    },
    {
      "pdfName": "43_Modern",
      "pageNo": 315,
      "index": 315,
      "code": "26039",
      "id": "43_Modern--i315--26039",
      "imageFile": "43_Modern--i315--26039--84e03.jpg",
      "imageSize": [
        500,
        353
      ]
    },
    {
      "pdfName": "43_Modern",
      "pageNo": 316,
      "index": 316,
      "code": "26040",
      "id": "43_Modern--i316--26040",
      "imageFile": "43_Modern--i316--26040--74885.jpg",
      "imageSize": [
        500,
        353
      ]
    },
    {
      "pdfName": "43_Modern",
      "pageNo": 317,
      "index": 317,
      "code": "26041",
      "id": "43_Modern--i317--26041",
      "imageFile": "43_Modern--i317--26041--6c3e7.jpg",
      "imageSize": [
        500,
        353
      ]
    },
    {
      "pdfName": "43_Modern",
      "pageNo": 318,
      "index": 318,
      "code": "26042",
      "id": "43_Modern--i318--26042",
      "imageFile": "43_Modern--i318--26042--09855.jpg",
      "imageSize": [
        500,
        353
      ]
    },
    {
      "pdfName": "43_Modern",
      "pageNo": 319,
      "index": 319,
      "code": "26043",
      "id": "43_Modern--i319--26043",
      "imageFile": "43_Modern--i319--26043--ad430.jpg",
      "imageSize": [
        500,
        353
      ]
    },
    {
      "pdfName": "43_Modern",
      "pageNo": 320,
      "index": 320,
      "code": "26044",
      "id": "43_Modern--i320--26044",
      "imageFile": "43_Modern--i320--26044--f5af5.jpg",
      "imageSize": [
        500,
        353
      ]
    },
    {
      "pdfName": "43_Modern",
      "pageNo": 321,
      "index": 321,
      "code": "26045",
      "id": "43_Modern--i321--26045",
      "imageFile": "43_Modern--i321--26045--f0ac5.jpg",
      "imageSize": [
        500,
        353
      ]
    },
    {
      "pdfName": "43_Modern",
      "pageNo": 322,
      "index": 322,
      "code": "26046",
      "id": "43_Modern--i322--26046",
      "imageFile": "43_Modern--i322--26046--b8a3f.jpg",
      "imageSize": [
        500,
        353
      ]
    },
    {
      "pdfName": "43_Modern",
      "pageNo": 323,
      "index": 323,
      "code": "26047",
      "id": "43_Modern--i323--26047",
      "imageFile": "43_Modern--i323--26047--67834.jpg",
      "imageSize": [
        500,
        353
      ]
    },
    {
      "pdfName": "43_Modern",
      "pageNo": 324,
      "index": 324,
      "code": "26048",
      "id": "43_Modern--i324--26048",
      "imageFile": "43_Modern--i324--26048--41aef.jpg",
      "imageSize": [
        500,
        353
      ]
    },
    {
      "pdfName": "43_Modern",
      "pageNo": 325,
      "index": 325,
      "code": "26049",
      "id": "43_Modern--i325--26049",
      "imageFile": "43_Modern--i325--26049--97742.jpg",
      "imageSize": [
        500,
        353
      ]
    },
    {
      "pdfName": "43_Modern",
      "pageNo": 326,
      "index": 326,
      "code": "26050",
      "id": "43_Modern--i326--26050",
      "imageFile": "43_Modern--i326--26050--03c05.jpg",
      "imageSize": [
        500,
        353
      ]
    },
    {
      "pdfName": "43_Modern",
      "pageNo": 327,
      "index": 327,
      "code": "26051",
      "id": "43_Modern--i327--26051",
      "imageFile": "43_Modern--i327--26051--0aa25.jpg",
      "imageSize": [
        500,
        353
      ]
    },
    {
      "pdfName": "43_Modern",
      "pageNo": 328,
      "index": 328,
      "code": "26052",
      "id": "43_Modern--i328--26052",
      "imageFile": "43_Modern--i328--26052--10188.jpg",
      "imageSize": [
        500,
        353
      ]
    },
    {
      "pdfName": "43_Modern",
      "pageNo": 329,
      "index": 329,
      "code": "26053",
      "id": "43_Modern--i329--26053",
      "imageFile": "43_Modern--i329--26053--afa4a.jpg",
      "imageSize": [
        500,
        353
      ]
    },
    {
      "pdfName": "43_Modern",
      "pageNo": 330,
      "index": 330,
      "code": "26054",
      "id": "43_Modern--i330--26054",
      "imageFile": "43_Modern--i330--26054--c1870.jpg",
      "imageSize": [
        500,
        353
      ]
    },
    {
      "pdfName": "43_Modern",
      "pageNo": 331,
      "index": 331,
      "code": "26055",
      "id": "43_Modern--i331--26055",
      "imageFile": "43_Modern--i331--26055--28bdf.jpg",
      "imageSize": [
        500,
        353
      ]
    },
    {
      "pdfName": "43_Modern",
      "pageNo": 332,
      "index": 332,
      "code": "26056",
      "id": "43_Modern--i332--26056",
      "imageFile": "43_Modern--i332--26056--52501.jpg",
      "imageSize": [
        500,
        353
      ]
    },
    {
      "pdfName": "43_Modern",
      "pageNo": 333,
      "index": 333,
      "code": "26057",
      "id": "43_Modern--i333--26057",
      "imageFile": "43_Modern--i333--26057--5f001.jpg",
      "imageSize": [
        500,
        353
      ]
    },
    {
      "pdfName": "43_Modern",
      "pageNo": 334,
      "index": 334,
      "code": "26058",
      "id": "43_Modern--i334--26058",
      "imageFile": "43_Modern--i334--26058--ebaae.jpg",
      "imageSize": [
        500,
        353
      ]
    },
    {
      "pdfName": "43_Modern",
      "pageNo": 335,
      "index": 335,
      "code": "26059",
      "id": "43_Modern--i335--26059",
      "imageFile": "43_Modern--i335--26059--8b5a2.jpg",
      "imageSize": [
        500,
        353
      ]
    },
    {
      "pdfName": "43_Modern",
      "pageNo": 336,
      "index": 336,
      "code": "26060",
      "id": "43_Modern--i336--26060",
      "imageFile": "43_Modern--i336--26060--fbbf9.jpg",
      "imageSize": [
        500,
        353
      ]
    },
    {
      "pdfName": "43_Modern",
      "pageNo": 337,
      "index": 337,
      "code": "26061",
      "id": "43_Modern--i337--26061",
      "imageFile": "43_Modern--i337--26061--563a5.jpg",
      "imageSize": [
        500,
        353
      ]
    },
    {
      "pdfName": "43_Modern",
      "pageNo": 338,
      "index": 338,
      "code": "26062",
      "id": "43_Modern--i338--26062",
      "imageFile": "43_Modern--i338--26062--00b42.jpg",
      "imageSize": [
        500,
        353
      ]
    },
    {
      "pdfName": "43_Modern",
      "pageNo": 339,
      "index": 339,
      "code": "26063",
      "id": "43_Modern--i339--26063",
      "imageFile": "43_Modern--i339--26063--41816.jpg",
      "imageSize": [
        500,
        353
      ]
    },
    {
      "pdfName": "43_Modern",
      "pageNo": 340,
      "index": 340,
      "code": "26064",
      "id": "43_Modern--i340--26064",
      "imageFile": "43_Modern--i340--26064--31764.jpg",
      "imageSize": [
        500,
        353
      ]
    },
    {
      "pdfName": "43_Modern",
      "pageNo": 341,
      "index": 341,
      "code": "26065",
      "id": "43_Modern--i341--26065",
      "imageFile": "43_Modern--i341--26065--e9adf.jpg",
      "imageSize": [
        500,
        353
      ]
    },
    {
      "pdfName": "43_Modern",
      "pageNo": 342,
      "index": 342,
      "code": "26066",
      "id": "43_Modern--i342--26066",
      "imageFile": "43_Modern--i342--26066--00cdf.jpg",
      "imageSize": [
        500,
        353
      ]
    },
    {
      "pdfName": "43_Modern",
      "pageNo": 343,
      "index": 343,
      "code": "26067",
      "id": "43_Modern--i343--26067",
      "imageFile": "43_Modern--i343--26067--3f617.jpg",
      "imageSize": [
        500,
        353
      ]
    },
    {
      "pdfName": "43_Modern",
      "pageNo": 344,
      "index": 344,
      "code": "26068",
      "id": "43_Modern--i344--26068",
      "imageFile": "43_Modern--i344--26068--36404.jpg",
      "imageSize": [
        500,
        353
      ]
    },
    {
      "pdfName": "43_Modern",
      "pageNo": 345,
      "index": 345,
      "code": "26069",
      "id": "43_Modern--i345--26069",
      "imageFile": "43_Modern--i345--26069--05769.jpg",
      "imageSize": [
        500,
        353
      ]
    },
    {
      "pdfName": "43_Modern",
      "pageNo": 346,
      "index": 346,
      "code": "26070",
      "id": "43_Modern--i346--26070",
      "imageFile": "43_Modern--i346--26070--3b8f6.jpg",
      "imageSize": [
        500,
        353
      ]
    },
    {
      "pdfName": "43_Modern",
      "pageNo": 347,
      "index": 347,
      "code": "26071",
      "id": "43_Modern--i347--26071",
      "imageFile": "43_Modern--i347--26071--81cf6.jpg",
      "imageSize": [
        500,
        353
      ]
    },
    {
      "pdfName": "43_Modern",
      "pageNo": 348,
      "index": 348,
      "code": "26072",
      "id": "43_Modern--i348--26072",
      "imageFile": "43_Modern--i348--26072--ada54.jpg",
      "imageSize": [
        500,
        353
      ]
    },
    {
      "pdfName": "43_Modern",
      "pageNo": 349,
      "index": 349,
      "code": "26073",
      "id": "43_Modern--i349--26073",
      "imageFile": "43_Modern--i349--26073--e7020.jpg",
      "imageSize": [
        500,
        353
      ]
    }
  ],
  "postersSample": [
    {
      "pdfName": "43_Modern",
      "pageNo": 19,
      "index": 19,
      "code": "25743",
      "id": "43_Modern--i19--25743",
      "imageFile": "43_Modern--i19--25743--39489.jpg",
      "imageSize": [
        500,
        353
      ]
    },
    {
      "pdfName": "43_Modern",
      "pageNo": 49,
      "index": 49,
      "code": "25773",
      "id": "43_Modern--i49--25773",
      "imageFile": "43_Modern--i49--25773--6b554.jpg",
      "imageSize": [
        500,
        353
      ]
    },
    {
      "pdfName": "43_Modern",
      "pageNo": 171,
      "index": 171,
      "code": "25895",
      "id": "43_Modern--i171--25895",
      "imageFile": "43_Modern--i171--25895--04cda.jpg",
      "imageSize": [
        500,
        353
      ]
    },
    {
      "pdfName": "43_Modern",
      "pageNo": 103,
      "index": 103,
      "code": "25827",
      "id": "43_Modern--i103--25827",
      "imageFile": "43_Modern--i103--25827--6879b.jpg",
      "imageSize": [
        500,
        353
      ]
    },
    {
      "pdfName": "43_Modern",
      "pageNo": 275,
      "index": 275,
      "code": "25999",
      "id": "43_Modern--i275--25999",
      "imageFile": "43_Modern--i275--25999--93eb2.jpg",
      "imageSize": [
        500,
        353
      ]
    }
  ]
}